README
setup.py
django_revisions.egg-info/PKG-INFO
django_revisions.egg-info/SOURCES.txt
django_revisions.egg-info/dependency_links.txt
django_revisions.egg-info/top_level.txt
revisions/__init__.py
revisions/admin.py
revisions/managers.py
revisions/middleware.py
revisions/models.py
revisions/shortcuts.py
revisions/views.py
revisions/tests/__init__.py
revisions/tests/admin.py
revisions/tests/models.py
revisions/tests/tests.py
revisions/tests/urls.py