Metadata-Version: 1.0
Name: django-revisions
Version: 0.3
Summary: Implements a revision trail for model instances in Django.
Home-page: http://stdbrouw.github.com/django-revisions/
Author: Stijn Debrouwere
Author-email: stijn@stdout.be
License: BSD
Download-URL: http://www.github.com/stdbrouw/django-revisions/tarball/master
Keywords: revisions versioning history
Platform: UNKNOWN
Classifier: Development Status :: 4 - Beta
Classifier: Environment :: Web Environment
Classifier: Framework :: Django
Classifier: Intended Audience :: Developers
Classifier: License :: OSI Approved :: BSD License
Classifier: Operating System :: OS Independent
Classifier: Programming Language :: Python
Classifier: Topic :: Software Development :: Libraries :: Python Modules
Classifier: Topic :: Utilities
